fpyo2ipa/__init__.py
fpyo2ipa/build.py
fpyo2ipa/Tools/__init__.py
fpyo2ipa/Tools/check_system.py
fpyo2ipa/Tools/check_venv.py
fpyo2ipa/Tools/unzip_assets.py
fpyo2ipa/assets/__init__.py
fpyo2ipa/assets/pyo2ipadist.zip
fpyo2ipa/beeware_tools/__init__.py
fpyo2ipa/beeware_tools/edit_beeware_project.py
fpyo2ipa/beeware_tools/the_app_py.py
fpyo2ipa/beeware_tools/the_localhost_py.py
fpyo2ipa-1.2.dist-info/LICENSE
fpyo2ipa-1.2.dist-info/METADATA
fpyo2ipa-1.2.dist-info/WHEEL
fpyo2ipa-1.2.dist-info/top_level.txt
fpyo2ipa-1.2.dist-info/RECORD
