Metadata-Version: 2.1
Name: fpyo2ipa
Version: 1.2
Summary: A package tool that allow you to built a python iOS apps with flet UI.
Home-page: https://github.com/SKbarbon/fpyo2ipa
Author: SKbarbon
Classifier: Programming Language :: Python :: 3
Classifier: Operating System :: MacOS :: MacOS X
License-File: LICENSE
Requires-Dist: briefcase (==0.3.14)
